<?xml version="1.0" encoding="UTF-8" ?>
<root>
    <layers eid="32843350">
        <name>Tilemap</name>
        <width>3968</width>
        <height>2176</height>
        <gridCellSize>16</gridCellSize>
    </layers>
    <layers eid="32843350">
        <name>Level Details</name>
        <winCondition>
            <surviveWaves>0</surviveWaves>
            <clearZombies>1</clearZombies>
            <resourceCount>1</resourceCount>
            <Resources>
                <Personnel>0</Personnel>
                <Ammunition>0</Ammunition>
                <DoS>0</DoS>
                <Fuel>0</Fuel>
                <Scrap>2000</Scrap>
            </Resources>
        </winCondition>
        <time>
            <day>0</day>
            <hour>12</hour>
            <minute>0</minute>
            <second>0</second>
        </time>
    </layers>
    <layers eid="32843350">
        <name>Swarms</name>
        <swarmCount>0</swarmCount>
    </layers>
    <layers eid="35163212">
        <name>Entities</name>
        <entities eid="95492584">
            <name>depot</name>
            <id>1</id>
            <health>1000</health>
            <x>1856</x>
            <y>960</y>
            <Resources>
                <Personnel>500</Personnel>
                <Ammunition>500</Ammunition>
                <DoS>500</DoS>
                <Fuel>500</Fuel>
                <Scrap>500</Scrap>
            </Resources>
        </entities>
        <entities eid="95492584">
            <name>Building</name>
            <id>2</id>
            <health>1000</health>
            <x>382</x>
            <y>994</y>
            <type>0</type>
            <alive>0</alive>
            <Resources>
                <Personnel>0</Personnel>
                <Ammunition>0</Ammunition>
                <DoS>0</DoS>
                <Fuel>0</Fuel>
                <Scrap>0</Scrap>
            </Resources>
            <art>draftArt/buildings/personnel.png</art>
        </entities>
        <entities eid="95492584">
            <name>Building</name>
            <id>3</id>
            <health>1000</health>
            <x>923</x>
            <y>1984</y>
            <originX>0</originX>
            <originY>0</originY>
            <type>1</type>
            <alive>0</alive>
            <Resources>
                <Personnel>0</Personnel>
                <Ammunition>0</Ammunition>
                <DoS>0</DoS>
                <Fuel>0</Fuel>
                <Scrap>0</Scrap>
            </Resources>
            <art>draftArt/buildings/ammunition.png</art>
        </entities>
        <entities eid="95492584">
            <name>Building</name>
            <id>4</id>
            <health>1000</health>
            <x>3238</x>
            <y>1323</y>
            <originX>0</originX>
            <originY>0</originY>
            <type>4</type>
            <alive>0</alive>
            <Resources>
                <Personnel>0</Personnel>
                <Ammunition>0</Ammunition>
                <DoS>0</DoS>
                <Fuel>0</Fuel>
                <Scrap>0</Scrap>
            </Resources>
            <art>draftArt/buildings/scrap.png</art>
        </entities>
        <entities>
        <name>Basic Zombie</name>
        <id>3</id>
        <health>500</health>
        <x>3207</x>
        <y>1716</y>
        <type>0</type>
<sight>500</sight>
    </entities>
    <entities>
        <name>Basic Zombie</name>
        <id>4</id>
        <health>500</health>
        <x>3091</x>
        <y>1781</y>
        <type>0</type>
<sight>500</sight>
    </entities>
    <entities>
        <name>Basic Zombie</name>
        <id>5</id>
        <health>500</health>
        <x>1471</x>
        <y>322</y>
        <type>0</type>
<sight>500</sight>
    </entities>
    <entities>
        <name>Basic Zombie</name>
        <id>6</id>
        <health>500</health>
        <x>262</x>
        <y>1282</y>
        <type>0</type>
<sight>500</sight>
    </entities>
    <entities>
        <name>Basic Zombie</name>
        <id>7</id>
        <health>500</health>
        <x>3387</x>
        <y>598</y>
<type>0</type>
<sight>500</sight>
    </entities>
    <entities>
        <name>Basic Zombie</name>
        <id>8</id>
        <health>500</health>
        <x>3342</x>
        <y>511</y>
<type>0</type>
<sight>500</sight>
    </entities>
    <entities>
        <name>Basic Zombie</name>
        <id>9</id>
        <health>500</health>
        <x>204</x>
        <y>948</y>
        <type>0</type>
<sight>500</sight>
    </entities>
    <entities>
        <name>Basic Zombie</name>
        <id>10</id>
        <health>500</health>
        <x>3202</x>
        <y>1977</y>
        <type>0</type>
<sight>500</sight>
    </entities>
    <entities>
        <name>Basic Zombie</name>
        <id>11</id>
        <health>500</health>
        <x>1056</x>
        <y>1783</y>
        <type>0</type>
<sight>500</sight>
    </entities>
    <entities>
        <name>Basic Zombie</name>
        <id>12</id>
        <health>500</health>
        <x>1472</x>
        <y>2090</y>
        <type>0</type>
<sight>500</sight>
    </entities>
    <entities>
        <name>Basic Zombie</name>
        <id>13</id>
        <health>500</health>
        <x>910</x>
        <y>679</y>
        <type>0</type>
<sight>500</sight>
    </entities>
    <entities>
        <name>Basic Zombie</name>
        <id>14</id>
        <health>500</health>
        <x>2817</x>
        <y>564</y>
        <type>0</type>
<sight>500</sight>
    </entities>
    <entities>
        <name>Basic Zombie</name>
        <id>15</id>
        <health>500</health>
        <x>2629</x>
        <y>586</y>
        <type>0</type>
<sight>500</sight>
    </entities>
    <entities>
        <name>Basic Zombie</name>
        <id>16</id>
        <health>500</health>
        <x>2689</x>
        <y>440</y>
        <type>0</type>
<sight>500</sight>
    </entities>
    <entities>
        <name>Basic Zombie</name>
        <id>17</id>
        <health>500</health>
        <x>2667</x>
        <y>380</y>
        <type>0</type>
<sight>500</sight>
    </entities>
    <entities>
        <name>Basic Zombie</name>
        <id>18</id>
        <health>500</health>
        <x>700</x>
        <y>1105</y>
        <type>0</type>
<sight>500</sight>
    </entities>
    <entities>
        <name>Basic Zombie</name>
        <id>19</id>
        <health>500</health>
        <x>2692</x>
        <y>578</y>
        <type>0</type>
<sight>500</sight>
    </entities>
    <entities>
        <name>Basic Zombie</name>
        <id>20</id>
        <health>500</health>
        <x>3061</x>
        <y>1859</y>
        <type>0</type>
<sight>500</sight>
    </entities>
    <entities>
        <name>Basic Zombie</name>
        <id>21</id>
        <health>500</health>
        <x>1917</x>
        <y>46</y>
        <type>0</type>
<sight>500</sight>
    </entities>
    <entities>
        <name>Basic Zombie</name>
        <id>22</id>
        <health>500</health>
        <x>2314</x>
        <y>1625</y>
        <type>0</type>
<sight>500</sight>
    </entities>
    <entities>
        <name>Basic Zombie</name>
        <id>23</id>
        <health>500</health>
        <x>214</x>
        <y>815</y>
        <type>0</type>
<sight>500</sight>
    </entities>
    <entities>
        <name>Basic Zombie</name>
        <id>24</id>
        <health>500</health>
        <x>2758</x>
        <y>1481</y>
        <type>0</type>
<sight>500</sight>
    </entities>
    <entities>
        <name>Basic Zombie</name>
        <id>25</id>
        <health>500</health>
        <x>3010</x>
        <y>232</y>
        <type>0</type>
<sight>500</sight>
    </entities>
    <entities>
        <name>Basic Zombie</name>
        <id>26</id>
        <health>500</health>
        <x>2822</x>
        <y>550</y>
        <type>0</type>
<sight>500</sight>
    </entities>
    <entities>
        <name>Basic Zombie</name>
        <id>27</id>
        <health>500</health>
        <x>74</x>
        <y>2055</y>
        <type>0</type>
<sight>500</sight>
    </entities>
    <entities>
        <name>Basic Zombie</name>
        <id>28</id>
        <health>500</health>
        <x>3781</x>
        <y>1113</y>
        <type>0</type>
<sight>500</sight>
    </entities>
    <entities>
        <name>Basic Zombie</name>
        <id>29</id>
        <health>500</health>
        <x>162</x>
        <y>2027</y>
        <type>0</type>
<sight>500</sight>
    </entities>
    <entities>
        <name>Basic Zombie</name>
        <id>30</id>
        <health>500</health>
        <x>3094</x>
        <y>2098</y>
        <type>0</type>
<sight>500</sight>
    </entities>
    <entities>
        <name>Basic Zombie</name>
        <id>31</id>
        <health>500</health>
        <x>753</x>
        <y>814</y>
        <type>0</type>
<sight>500</sight>
    </entities>
    <entities>
        <name>Basic Zombie</name>
        <id>32</id>
        <health>500</health>
        <x>3704</x>
        <y>71</y>
        <type>0</type>
<sight>500</sight>
    </entities>
    <entities>
        <name>Basic Zombie</name>
        <id>33</id>
        <health>500</health>
        <x>1221</x>
        <y>824</y>
        <type>0</type>
<sight>500</sight>
    </entities>
    <entities>
        <name>Basic Zombie</name>
        <id>34</id>
        <health>500</health>
        <x>1289</x>
        <y>1226</y>
        <type>0</type>
<sight>500</sight>
    </entities>
    <entities>
        <name>Basic Zombie</name>
        <id>35</id>
        <health>500</health>
        <x>728</x>
        <y>1131</y>
        <type>0</type>
<sight>500</sight>
    </entities>
    <entities>
        <name>Basic Zombie</name>
        <id>36</id>
        <health>500</health>
        <x>3950</x>
        <y>1502</y>
        <type>0</type>
<sight>500</sight>
    </entities>
    <entities>
        <name>Basic Zombie</name>
        <id>37</id>
        <health>500</health>
        <x>402</x>
        <y>926</y>
        <type>0</type>
<sight>500</sight>
    </entities>
    <entities>
        <name>Basic Zombie</name>
        <id>38</id>
        <health>500</health>
        <x>761</x>
        <y>555</y>
        <type>0</type>
<sight>500</sight>
    </entities>
    <entities>
        <name>Basic Zombie</name>
        <id>39</id>
        <health>500</health>
        <x>865</x>
        <y>142</y>
        <type>0</type>
<sight>500</sight>
    </entities>
    <entities>
        <name>Basic Zombie</name>
        <id>40</id>
        <health>500</health>
        <x>344</x>
        <y>327</y>
        <type>0</type>
<sight>500</sight>
    </entities>
    <entities>
        <name>Basic Zombie</name>
        <id>41</id>
        <health>500</health>
        <x>190</x>
        <y>446</y>
        <type>0</type>
<sight>500</sight>
    </entities>
    <entities>
        <name>Basic Zombie</name>
        <id>42</id>
        <health>500</health>
        <x>2690</x>
        <y>1311</y>
        <type>0</type>
<sight>500</sight>
    </entities>
    <entities>
        <name>Basic Zombie</name>
        <id>43</id>
        <health>500</health>
        <x>2940</x>
        <y>250</y>
        <type>0</type>
<sight>500</sight>
    </entities>
    <entities>
        <name>Basic Zombie</name>
        <id>44</id>
        <health>500</health>
        <x>303</x>
        <y>1458</y>
        <type>0</type>
<sight>500</sight>
    </entities>
    <entities>
        <name>Basic Zombie</name>
        <id>45</id>
        <health>500</health>
        <x>566</x>
        <y>1545</y>
        <type>0</type>
<sight>500</sight>
    </entities>
    <entities>
        <name>Basic Zombie</name>
        <id>46</id>
        <health>500</health>
        <x>3752</x>
        <y>310</y>
        <type>0</type>
<sight>500</sight>
    </entities>
    <entities>
        <name>Basic Zombie</name>
        <id>47</id>
        <health>500</health>
        <x>3261</x>
        <y>969</y>
        <type>0</type>
<sight>500</sight>
    </entities>
    <entities>
        <name>Basic Zombie</name>
        <id>48</id>
        <health>500</health>
        <x>559</x>
        <y>141</y>
        <type>0</type>
<sight>500</sight>
    </entities>
    <entities>
        <name>Basic Zombie</name>
        <id>49</id>
        <health>500</health>
        <x>1844</x>
        <y>42</y>
        <type>0</type>
<sight>500</sight>
    </entities>
    <entities>
        <name>Basic Zombie</name>
        <id>50</id>
        <health>500</health>
        <x>3571</x>
        <y>1354</y>
        <type>0</type>
<sight>500</sight>
    </entities>
    <entities>
        <name>Basic Zombie</name>
        <id>51</id>
        <health>500</health>
        <x>1609</x>
        <y>1790</y>
        <type>0</type>
<sight>500</sight>
    </entities>
    <entities>
        <name>Basic Zombie</name>
        <id>52</id>
        <health>500</health>
        <x>550</x>
        <y>1029</y>
        <type>0</type>
<sight>500</sight>
    </entities>
    <entities>
        <name>Basic Zombie</name>
        <id>53</id>
        <health>500</health>
        <x>1879</x>
        <y>1606</y>
        <type>0</type>
<sight>500</sight>
    </entities>
    <entities>
        <name>Basic Zombie</name>
        <id>54</id>
        <health>500</health>
        <x>3833</x>
        <y>1312</y>
        <type>0</type>
<sight>500</sight>
    </entities>
    <entities>
        <name>Basic Zombie</name>
        <id>55</id>
        <health>500</health>
        <x>2729</x>
        <y>1341</y>
        <type>0</type>
<sight>500</sight>
    </entities>
    <entities>
        <name>Basic Zombie</name>
        <id>56</id>
        <health>500</health>
        <x>1123</x>
        <y>125</y>
        <type>0</type>
<sight>500</sight>
    </entities>
    <entities>
        <name>Basic Zombie</name>
        <id>57</id>
        <health>500</health>
        <x>3080</x>
        <y>1432</y>
        <type>0</type>
<sight>500</sight>
    </entities>
    <entities>
        <name>Basic Zombie</name>
        <id>58</id>
        <health>500</health>
        <x>3665</x>
        <y>414</y>
        <type>0</type>
<sight>500</sight>
    </entities>
    <entities>
        <name>Basic Zombie</name>
        <id>59</id>
        <health>500</health>
        <x>2491</x>
        <y>773</y>
        <type>0</type>
<sight>500</sight>
    </entities>
    <entities>
        <name>Basic Zombie</name>
        <id>60</id>
        <health>500</health>
        <x>1076</x>
        <y>1968</y>
        <type>0</type>
<sight>500</sight>
    </entities>
    <entities>
        <name>Basic Zombie</name>
        <id>61</id>
        <health>500</health>
        <x>2836</x>
        <y>269</y>
        <type>0</type>
<sight>500</sight>
    </entities>
    <entities>
        <name>Basic Zombie</name>
        <id>62</id>
        <health>500</health>
        <x>3490</x>
        <y>1685</y>
        <type>0</type>
<sight>500</sight>
    </entities>
    <entities>
        <name>Basic Zombie</name>
        <id>63</id>
        <health>500</health>
        <x>662</x>
        <y>1593</y>
        <type>0</type>
<sight>500</sight>
    </entities>
    <entities>
        <name>Basic Zombie</name>
        <id>64</id>
        <health>500</health>
        <x>14</x>
        <y>1453</y>
        <type>0</type>
<sight>500</sight>
    </entities>
    <entities>
        <name>Basic Zombie</name>
        <id>65</id>
        <health>500</health>
        <x>664</x>
        <y>307</y>
        <type>0</type>
<sight>500</sight>
    </entities>
    <entities>
        <name>Basic Zombie</name>
        <id>66</id>
        <health>500</health>
        <x>617</x>
        <y>1839</y>
        <type>0</type>
<sight>500</sight>
    </entities>
    <entities>
        <name>Basic Zombie</name>
        <id>67</id>
        <health>500</health>
        <x>2363</x>
        <y>424</y>
        <type>0</type>
<sight>500</sight>
    </entities>
    <entities>
        <name>Basic Zombie</name>
        <id>68</id>
        <health>500</health>
        <x>1696</x>
        <y>1838</y>
        <type>0</type>
<sight>500</sight>
    </entities>
    <entities>
        <name>Basic Zombie</name>
        <id>69</id>
        <health>500</health>
        <x>2580</x>
        <y>483</y>
        <type>0</type>
<sight>500</sight>
    </entities>
    <entities>
        <name>Basic Zombie</name>
        <id>70</id>
        <health>500</health>
        <x>1716</x>
        <y>1587</y>
        <type>0</type>
<sight>500</sight>
    </entities>
    <entities>
        <name>Basic Zombie</name>
        <id>71</id>
        <health>500</health>
        <x>2077</x>
        <y>351</y>
        <type>0</type>
<sight>500</sight>
    </entities>
    <entities>
        <name>Basic Zombie</name>
        <id>72</id>
        <health>500</health>
        <x>3466</x>
        <y>1762</y>
        <type>0</type>
<sight>500</sight>
    </entities>
    <entities>
        <name>Basic Zombie</name>
        <id>73</id>
        <health>500</health>
        <x>3013</x>
        <y>1544</y>
        <type>0</type>
<sight>500</sight>
    </entities>
    <entities>
        <name>Basic Zombie</name>
        <id>74</id>
        <health>500</health>
        <x>1383</x>
        <y>1671</y>
        <type>0</type>
<sight>500</sight>
    </entities>
    <entities>
        <name>Basic Zombie</name>
        <id>75</id>
        <health>500</health>
        <x>1252</x>
        <y>1221</y>
        <type>0</type>
<sight>500</sight>
    </entities>
    <entities>
        <name>Basic Zombie</name>
        <id>76</id>
        <health>500</health>
        <x>2727</x>
        <y>671</y>
        <type>0</type>
<sight>500</sight>
    </entities>
    <entities>
        <name>Basic Zombie</name>
        <id>77</id>
        <health>500</health>
        <x>3281</x>
        <y>2073</y>
        <type>0</type>
<sight>500</sight>
    </entities>
    <entities>
        <name>Basic Zombie</name>
        <id>78</id>
        <health>500</health>
        <x>787</x>
        <y>1503</y>
        <type>0</type>
<sight>500</sight>
    </entities>
    <entities>
        <name>Basic Zombie</name>
        <id>79</id>
        <health>500</health>
        <x>2623</x>
        <y>385</y>
        <type>0</type>
<sight>500</sight>
    </entities>
    <entities>
        <name>Basic Zombie</name>
        <id>80</id>
        <health>500</health>
        <x>1030</x>
        <y>201</y>
        <type>0</type>
<sight>500</sight>
    </entities>
    <entities>
        <name>Basic Zombie</name>
        <id>81</id>
        <health>500</health>
        <x>378</x>
        <y>2087</y>
        <type>0</type>
<sight>500</sight>
    </entities>
    <entities>
        <name>Basic Zombie</name>
        <id>82</id>
        <health>500</health>
        <x>2127</x>
        <y>2174</y>
        <type>0</type>
<sight>500</sight>
    </entities>
    <entities>
        <name>Basic Zombie</name>
        <id>83</id>
        <health>500</health>
        <x>878</x>
        <y>472</y>
        <type>0</type>
<sight>500</sight>
    </entities>
    <entities>
        <name>Basic Zombie</name>
        <id>84</id>
        <health>500</health>
        <x>2519</x>
        <y>1875</y>
        <type>0</type>
<sight>500</sight>
    </entities>
    <entities>
        <name>Basic Zombie</name>
        <id>85</id>
        <health>500</health>
        <x>233</x>
        <y>824</y>
        <type>0</type>
<sight>500</sight>
    </entities>
    <entities>
        <name>Basic Zombie</name>
        <id>86</id>
        <health>500</health>
        <x>162</x>
        <y>693</y>
        <type>0</type>
<sight>500</sight>
    </entities>
    <entities>
        <name>Basic Zombie</name>
        <id>87</id>
        <health>500</health>
        <x>732</x>
        <y>1907</y>
        <type>0</type>
<sight>500</sight>
    </entities>
    <entities>
        <name>Basic Zombie</name>
        <id>88</id>
        <health>500</health>
        <x>3840</x>
        <y>804</y>
        <type>0</type>
<sight>500</sight>
    </entities>
    <entities>
        <name>Basic Zombie</name>
        <id>89</id>
        <health>500</health>
        <x>3053</x>
        <y>1443</y>
        <type>0</type>
<sight>500</sight>
    </entities>
    <entities>
        <name>Basic Zombie</name>
        <id>90</id>
        <health>500</health>
        <x>315</x>
        <y>1273</y>
        <type>0</type>
<sight>500</sight>
    </entities>
    <entities>
        <name>Basic Zombie</name>
        <id>91</id>
        <health>500</health>
        <x>1828</x>
        <y>1623</y>
        <type>0</type>
<sight>500</sight>
    </entities>
    <entities>
        <name>Basic Zombie</name>
        <id>92</id>
        <health>500</health>
        <x>3829</x>
        <y>1955</y>
        <type>0</type>
<sight>500</sight>
    </entities>
    <entities>
        <name>Basic Zombie</name>
        <id>93</id>
        <health>500</health>
        <x>3698</x>
        <y>1836</y>
        <type>0</type>
<sight>500</sight>
    </entities>
    <entities>
        <name>Basic Zombie</name>
        <id>94</id>
        <health>500</health>
        <x>3068</x>
        <y>1353</y>
        <type>0</type>
<sight>500</sight>
    </entities>
    <entities>
        <name>Basic Zombie</name>
        <id>95</id>
        <health>500</health>
        <x>1435</x>
        <y>2085</y>
        <type>0</type>
<sight>500</sight>
    </entities>
    <entities>
        <name>Basic Zombie</name>
        <id>96</id>
        <health>500</health>
        <x>1268</x>
        <y>757</y>
        <type>0</type>
<sight>500</sight>
    </entities>
    <entities>
        <name>Basic Zombie</name>
        <id>97</id>
        <health>500</health>
        <x>2200</x>
        <y>233</y>
        <type>0</type>
<sight>500</sight>
    </entities>
    <entities>
        <name>Basic Zombie</name>
        <id>98</id>
        <health>500</health>
        <x>3261</x>
        <y>537</y>
        <type>0</type>
<sight>500</sight>
    </entities>
    <entities>
        <name>Basic Zombie</name>
        <id>99</id>
        <health>500</health>
        <x>232</x>
        <y>1158</y>
        <type>0</type>
<sight>500</sight>
    </entities>
    <entities>
        <name>Basic Zombie</name>
        <id>100</id>
        <health>500</health>
        <x>1531</x>
        <y>96</y>
        <type>0</type>
<sight>500</sight>
    </entities>
    <entities>
        <name>Basic Zombie</name>
        <id>101</id>
        <health>500</health>
        <x>370</x>
        <y>775</y>
        <type>0</type>
<sight>500</sight>
    </entities>
    <entities>
        <name>Basic Zombie</name>
        <id>102</id>
        <health>500</health>
        <x>896</x>
        <y>1433</y>
        <type>0</type>
<sight>500</sight>
    </entities>
    <entities>
        <name>Basic Zombie</name>
        <id>103</id>
        <health>5000</health>
        <x>896</x>
        <y>1433</y>
        <type>1</type>
<sight>500</sight>
    </entities>
    </layers>
</root>
